[{
  "diagramId": "26",
  "diagramVal": ["54,2%", "45,8%"],
  "roundTitle": "2017",
  "item1": [{
    "title": "Всего по социально направленным программам",
    "strong": true,
    "value1": "991,3",
    "value2": "100%"
  }, {
    "title": "Социальная поддержка жителей города Москвы",
    "value1": "391,2",
    "value2": "39,5%"
  }, {
    "title": "Столичное образование",
    "value1": "276,2",
    "value2": "27,9"
  }, {
    "title": "Столичное здравоохранение",
    "value1": "233,0",
    "value2": "23,5%"
  }, {
    "title": "Спорт Москвы",
    "value1": "45,7",
    "value2": "4,6%",
    "overwidth": true
  }, {
    "title": "Культура Москвы",
    "value1": "45,2",
    "value2": "4,6%",
    "overwidth": true
  }],
  "item2": [{
    "title": "Всего по другим программам",
    "strong": true,
    "value1": "991,3",
    "value2": "100%"
  }, {
    "title": "Другая программа 1",
    "value1": "391,2",
    "value2": "39,5%"
  }, {
    "title": "Другая программа 2",
    "value1": "276,2",
    "value2": "27,9"
  }, {
    "title": "Другая программа 3",
    "value1": "233,0",
    "value2": "23,5%"
  }]
}, {
  "diagramId": "27",
  "diagramVal": ["40,0%", "60,0%"],
  "roundTitle": "2018",
  "item1": [{
    "title": "Всего по социально направленным программам",
    "strong": true,
    "value1": "991,3",
    "value2": "100%"
  }, {
    "title": "Социальная поддержка жителей города Москвы",
    "value1": "391,2",
    "value2": "39,5%"
  }, {
    "title": "Столичное образование",
    "value1": "276,2",
    "value2": "27,9"
  }, {
    "title": "Столичное здравоохранение",
    "value1": "233,0",
    "value2": "23,5%"
  }, {
    "title": "Спорт Москвы",
    "value1": "45,7",
    "value2": "4,6%",
    "overwidth": true
  }, {
    "title": "Культура Москвы",
    "value1": "45,2",
    "value2": "4,6%",
    "overwidth": true
  }],
  "item2": [{
    "title": "Всего по другим программам",
    "strong": true,
    "value1": "991,3",
    "value2": "100%"
  }, {
    "title": "Другая программа 1",
    "value1": "391,2",
    "value2": "39,5%"
  }, {
    "title": "Другая программа 2",
    "value1": "276,2",
    "value2": "27,9"
  }, {
    "title": "Другая программа 3",
    "value1": "233,0",
    "value2": "23,5%"
  }]
},{
  "diagramId": "28",
  "diagramVal": ["60,0%", "40,0%"],
  "roundTitle": "2019",
  "item1": [{
    "title": "Всего по социально направленным программам",
    "strong": true,
    "value1": "991,3",
    "value2": "100%"
  }, {
    "title": "Социальная поддержка жителей города Москвы",
    "value1": "391,2",
    "value2": "39,5%"
  }, {
    "title": "Столичное образование",
    "value1": "276,2",
    "value2": "27,9"
  }, {
    "title": "Столичное здравоохранение",
    "value1": "233,0",
    "value2": "23,5%"
  }, {
    "title": "Спорт Москвы",
    "value1": "45,7",
    "value2": "4,6%",
    "overwidth": true
  }, {
    "title": "Культура Москвы",
    "value1": "45,2",
    "value2": "4,6%",
    "overwidth": true
  }],
  "item2": [{
    "title": "Всего по другим программам",
    "strong": true,
    "value1": "991,3",
    "value2": "100%"
  }, {
    "title": "Другая программа 1",
    "value1": "391,2",
    "value2": "39,5%"
  }, {
    "title": "Другая программа 2",
    "value1": "276,2",
    "value2": "27,9"
  }, {
    "title": "Другая программа 3",
    "value1": "233,0",
    "value2": "23,5%"
  }]
},{
  "diagramId": "29",
  "diagramVal": ["70,0%", "30,0%"],
  "roundTitle": "2016",
  "item1": [{
    "title": "Всего по социально направленным программам",
    "strong": true,
    "value1": "991,3",
    "value2": "100%"
  }, {
    "title": "Социальная поддержка жителей города Москвы",
    "value1": "391,2",
    "value2": "39,5%"
  }, {
    "title": "Столичное образование",
    "value1": "276,2",
    "value2": "27,9"
  }, {
    "title": "Столичное здравоохранение",
    "value1": "233,0",
    "value2": "23,5%"
  }, {
    "title": "Спорт Москвы",
    "value1": "45,7",
    "value2": "4,6%",
    "overwidth": true
  }, {
    "title": "Культура Москвы",
    "value1": "45,2",
    "value2": "4,6%",
    "overwidth": true
  }],
  "item2": [{
    "title": "Всего по другим программам",
    "strong": true,
    "value1": "991,3",
    "value2": "100%"
  }, {
    "title": "Другая программа 1",
    "value1": "391,2",
    "value2": "39,5%"
  }, {
    "title": "Другая программа 2",
    "value1": "276,2",
    "value2": "27,9"
  }, {
    "title": "Другая программа 3",
    "value1": "233,0",
    "value2": "23,5%"
  }]
},{
  "diagramId": "30",
  "diagramVal": ["75,0%", "25,0%"],
  "roundTitle": "2016",
  "item1": [{
    "title": "Всего по социально направленным программам",
    "strong": true,
    "value1": "991,3",
    "value2": "100%"
  }, {
    "title": "Социальная поддержка жителей города Москвы",
    "value1": "391,2",
    "value2": "39,5%"
  }, {
    "title": "Столичное образование",
    "value1": "276,2",
    "value2": "27,9"
  }, {
    "title": "Столичное здравоохранение",
    "value1": "233,0",
    "value2": "23,5%"
  }, {
    "title": "Спорт Москвы",
    "value1": "45,7",
    "value2": "4,6%",
    "overwidth": true
  }, {
    "title": "Культура Москвы",
    "value1": "45,2",
    "value2": "4,6%",
    "overwidth": true
  }],
  "item2": [{
    "title": "Всего по другим программам",
    "strong": true,
    "value1": "991,3",
    "value2": "100%"
  }, {
    "title": "Другая программа 1",
    "value1": "391,2",
    "value2": "39,5%"
  }, {
    "title": "Другая программа 2",
    "value1": "276,2",
    "value2": "27,9"
  }, {
    "title": "Другая программа 3",
    "value1": "233,0",
    "value2": "23,5%"
  }]
}

]
